arcanna_mcp_server/__init__.py
arcanna_mcp_server/constants.py
arcanna_mcp_server/environment.py
arcanna_mcp_server/server.py
arcanna_mcp_server/models/base_resource.py
arcanna_mcp_server/models/filters.py
arcanna_mcp_server/models/generic_events.py
arcanna_mcp_server/models/metrics.py
arcanna_mcp_server/models/resource_type.py
arcanna_mcp_server/tools/__init__.py
arcanna_mcp_server/tools/agentic.py
arcanna_mcp_server/tools/custom_code_block.py
arcanna_mcp_server/tools/generic_events.py
arcanna_mcp_server/tools/health_check.py
arcanna_mcp_server/tools/jobs.py
arcanna_mcp_server/tools/metrics.py
arcanna_mcp_server/tools/rag.py
arcanna_mcp_server/tools/resources.py
arcanna_mcp_server/tools/system.py
arcanna_mcp_server/utils/__init__.py
arcanna_mcp_server/utils/exceptions_handler.py
arcanna_mcp_server/utils/post_data.py
arcanna_mcp_server/utils/tool_exception_response.py
arcanna_mcp_server/utils/tool_scopes.py
arcanna_mcp_server-0.1.31.dist-info/METADATA
arcanna_mcp_server-0.1.31.dist-info/WHEEL
arcanna_mcp_server-0.1.31.dist-info/entry_points.txt
arcanna_mcp_server-0.1.31.dist-info/RECORD
