Metadata-Version: 2.4
Name: arcanna-mcp-server
Version: 0.1.31
Summary: The Arcanna MCP server allows user to interact with Arcanna's AI use cases through the Model Context Protocol (MCP).
Project-URL: homepage, https://github.com/siscale/arcanna-mcp-server
Author-email: DevSiscale <dev@siscale.com>
Requires-Python: >=3.10
Requires-Dist: aiohttp>=3.12.13
Requires-Dist: fastapi>=0.115.6
Requires-Dist: mcp[cli]>=1.2.1
Requires-Dist: requests>=2.32.3
Requires-Dist: starlette>=0.46.0
Requires-Dist: uv>=0.6.9
